flex_alchemy/__init__.py
flex_alchemy/activerecord.py
flex_alchemy/builders/__init__.py
flex_alchemy/builders/base.py
flex_alchemy/builders/delete.py
flex_alchemy/builders/insert.py
flex_alchemy/builders/select.py
flex_alchemy/builders/update.py
flex_alchemy/exceptions.py
flex_alchemy/scopes/__init__.py
flex_alchemy/scopes/softdelete.py
flex_alchemy/session.py
flex_alchemy-0.1.1.dist-info/LICENSE
flex_alchemy-0.1.1.dist-info/METADATA
flex_alchemy-0.1.1.dist-info/WHEEL
flex_alchemy-0.1.1.dist-info/RECORD
