Metadata-Version: 2.3
Name: flex-alchemy
Version: 0.1.1
Summary: SQLAlchemy with Active Record - a fluent query builder and ActiveRecord implementation for SQLAlchemy
License: MIT
Author: Sam Yao
Author-email: turisesonia@gmail.com
Requires-Python: >=3.9
Classifier: License :: OSI Approved :: MIT License
Classifier: Programming Language :: Python :: 3
Classifier: Programming Language :: Python :: 3.9
Classifier: Programming Language :: Python :: 3.10
Classifier: Programming Language :: Python :: 3.11
Classifier: Programming Language :: Python :: 3.12
Classifier: Programming Language :: Python :: 3.13
Requires-Dist: sqlalchemy (>=2.0,<3.0.0)
